distanX/CloudDistance.py
distanX/Curve2Line.py
distanX/Line2ROI.py
distanX/__init__.py
distanx-0.2.2.dist-info/LICENSE
distanx-0.2.2.dist-info/METADATA
distanx-0.2.2.dist-info/WHEEL
distanx-0.2.2.dist-info/top_level.txt
distanx-0.2.2.dist-info/RECORD
