Metadata-Version: 2.1
Name: distanX
Version: 0.2.2
Summary: A Python Package for Getting ROIs and Calculating Group Distances in Spatial Transcriptomics Data
Home-page: https://github.com/kusurin/distanX
Author: kusurin
License: AGPL-3.0
Classifier: Programming Language :: Python :: 3
Classifier: License :: OSI Approved :: GNU Affero General Public License v3
Classifier: Operating System :: OS Independent
Requires-Python: >=3.6
License-File: LICENSE
Requires-Dist: opencv-python
Requires-Dist: anndata
Requires-Dist: pandas
Requires-Dist: numpy
Requires-Dist: joblib
